Workbook

Sheet Dataset
A1: Firm_ID | B1: Status | C1: Status_Label | D1: Sample | E1: Current_Ratio | F1: Quick_Ratio | G1: Debt_to_Equity | H1: Interest_Coverage | I1: ROA | J1: Net_Profit_Margin | K1: Asset_Turnover | L1: Firm_Size_lnTA
A2: F001 | B2: 0 | C2: =IF(B2=1,"Bankrupt","Non-Bankrupt") -> Non-Bankrupt | D2: Train | E2: 2.2426 | F2: 1.4365 | G2: 1.2011 | H2: 8.627 | I2: 0.0103 | J2: 0.0045 | K2: 1.9683 | L2: 15.8613
A3: F002 | B3: 0 | C3: =IF(B3=1,"Bankrupt","Non-Bankrupt") -> Non-Bankrupt | D3: Train | E3: 1.7882 | F3: 2.6563 | G3: 1.4449 | H3: 1.8385 | I3: 0.2 | J3: 0.0314 | K3: 1.651 | L3: 15.2593
A4: F003 | B4: 0 | C4: =IF(B4=1,"Bankrupt","Non-Bankrupt") -> Non-Bankrupt | D4: Train | E4: 1.6322 | F4: 0.7736 | G4: 0.7511 | H4: 10.5304 | I4: 0.0959 | J4: 0.0968 | K4: 2.241 | L4: 14.5184
A5: F004 | B5: 1 | C5: =IF(B5=1,"Bankrupt","Non-Bankrupt") -> Bankrupt | D5: Train | E5: 1.5814 | F5: 0.7221 | G5: 1.7621 | H5: 2.4634 | I5: -0.0466 | J5: -0.0273 | K5: 0.5951 | L5: 14.7289
A6: F005 | B6: 1 | C6: =IF(B6=1,"Bankrupt","Non-Bankrupt") -> Bankrupt | D6: Train | E6: 1.5041 | F6: 2.0542 | G6: 0.8809 | H6: 3.346 | I6: 0.0487 | J6: -0.0697 | K6: 0.2 | L6: 13.7158
A7: F006 | B7: 0 | C7: =IF(B7=1,"Bankrupt","Non-Bankrupt") -> Non-Bankrupt | D7: Train | E7: 1.2706 | F7: 1.971 | G7: 0.8306 | H7: 6.7852 | I7: 0.0918 | J7: 0.0166 | K7: 0.784 | L7: 14.0959
A8: F007 | B8: 1 | C8: =IF(B8=1,"Bankrupt","Non-Bankrupt") -> Bankrupt | D8: Train | E8: 1.3404 | F8: 0.6404 | G8: 2.0716 | H8: 2.6839 | I8: -0.0751 | J8: -0.0133 | K8: 0.9162 | L8: 11.139
A9: F008 | B9: 0 | C9: =IF(B9=1,"Bankrupt","Non-Bankrupt") -> Non-Bankrupt | D9: Test | E9: 1.7113 | F9: 1.5416 | G9: 1.3305 | H9: 7.3179 | I9: 0.0062 | J9: 0.0923 | K9: 1.2332 | L9: 14.9625
A10: F009 | B10: 0 | C10: =IF(B10=1,"Bankrupt","Non-Bankrupt") -> Non-Bankrupt | D10: Test | E10: 1.3164 | F10: 1.3917 | G10: 1.1098 | H10: 1.2446 | I10: 0.0302 | J10: 0.1179 | K10: 1.1123 | L10: 14.3434
A11: F010 | B11: 0 | C11: =IF(B11=1,"Bankrupt","Non-Bankrupt") -> Non-Bankrupt | D11: Train | E11: 1.469 | F11: 1.6132 | G11: 1.3383 | H11: 10.1626 | I11: -0.0217 | J11: 0.0134 | K11: 0.8172 | L11: 15.8378
A12: F011 | B12: 0 | C12: =IF(B12=1,"Bankrupt","Non-Bankrupt") -> Non-Bankrupt | D12: Train | E12: 1.6538 | F12: 1.2646 | G12: 1.4538 | H12: 1.6822 | I12: 0.1307 | J12: 0.0953 | K12: 1.4481 | L12: 13.9759
A13: F012 | B13: 0 | C13: =IF(B13=1,"Bankrupt","Non-Bankrupt") -> Non-Bankrupt | D13: Train | E13: 1.6909 | F13: 0.9779 | G13: 0.782 | H13: 3.949 | I13: -0.003 | J13: 0.0609 | K13: 1.1863 | L13: 16.437
... A181: F180 | B181: 1 | C181: =IF(B181=1,"Bankrupt","Non-Bankrupt") -> Bankrupt | D181: Train | E181: 0.9884 | F181: 1.3489 | G181: 0.6877 | H181: 3.2917 | I181: -0.139 | J181: 0.0511 | K181: 0.8043 | L181: 15.8796

Sheet Codebook
A1: Codebook / Variable View
A3: Variable | B3: Label | C3: Definition | D3: Group | E3: Type / Decimals | F3: Values
A4: Firm_ID | B4: Firm identifier | C4: Anonymised company code (F001–F180) | D4: ID | E4: String
A5: Status | B5: Bankruptcy status | C5: Firm status at the time of observation | D5: Dependent variable | E5: Numeric, 0 | F5: 0 = Non-Bankrupt; 1 = Bankrupt
A6: Status_Label | B6: Status (text) | C6: Text label of Status | D6: — | E6: String
A7: Sample | B7: Train/Test split | C7: Stratified 70/30 split used for ML models (Train n = 126, Test n = 54) | D7: — | E7: String | F7: Train; Test
A8: Current_Ratio | B8: Current Ratio | C8: Current assets / Current liabilities | D8: Liquidity | E8: Numeric, 4 | F8: Scale
A9: Quick_Ratio | B9: Quick Ratio | C9: (Current assets − Inventories) / Current liabilities | D9: Liquidity | E9: Numeric, 4 | F9: Scale
A10: Debt_to_Equity | B10: Debt-to-Equity | C10: Total liabilities / Shareholders' equity | D10: Leverage | E10: Numeric, 4 | F10: Scale
A11: Interest_Coverage | B11: Interest Coverage | C11: EBIT / Interest expense | D11: Leverage | E11: Numeric, 4 | F11: Scale
A12: ROA | B12: ROA | C12: Net income / Total assets | D12: Profitability | E12: Numeric, 4 | F12: Scale
A13: Net_Profit_Margin | B13: Net Profit Margin | C13: Net income / Net sales | D13: Profitability | E13: Numeric, 4 | F13: Scale
A14: Asset_Turnover | B14: Asset Turnover | C14: Net sales / Total assets | D14: Efficiency | E14: Numeric, 4 | F14: Scale
A15: Firm_Size_lnTA | B15: Firm Size (ln TA) | C15: Natural logarithm of total assets | D15: Size | E15: Numeric, 4 | F15: Scale

Sheet T5.1 Descriptives
A1: Table 5.1 – Descriptive Statistics of Financial Indicators (N = 180)
A3: Indicator | B3: N | C3: Mean | D3: Std. Dev. | E3: Minimum | F3: Maximum | H3: Reported Mean | I3: Reported SD | J3: Reported Min | K3: Reported Max | L3: Match
A4: Current Ratio | B4: =COUNT(Dataset!$E$2:$E$181) -> 180 | C4: =AVERAGE(Dataset!$E$2:$E$181) -> 1.5296011 | D4: =STDEV(Dataset!$E$2:$E$181) -> 0.51840146 | E4: =MIN(Dataset!$E$2:$E$181) -> 0.2 | F4: =MAX(Dataset!$E$2:$E$181) -> 3.005 | H4: 1.53 | I4: 0.518 | J4: 0.2 | K4: 3.005 | L4: =IF(AND(ROUND(C4,3)=H4,ROUND(D4,3)=I4,ROUND(E4,3)=J4,ROUND(F4,3)=K4),"✓","✗") -> ✓
A5: Quick Ratio | B5: =COUNT(Dataset!$F$2:$F$181) -> 180 | C5: =AVERAGE(Dataset!$F$2:$F$181) -> 1.1330261 | D5: =STDEV(Dataset!$F$2:$F$181) -> 0.51939868 | E5: =MIN(Dataset!$F$2:$F$181) -> 0.1 | F5: =MAX(Dataset!$F$2:$F$181) -> 3 | H5: 1.133 | I5: 0.519 | J5: 0.1 | K5: 3 | L5: =IF(AND(ROUND(C5,3)=H5,ROUND(D5,3)=I5,ROUND(E5,3)=J5,ROUND(F5,3)=K5),"✓","✗") -> ✓
A6: Debt-to-Equity | B6: =COUNT(Dataset!$G$2:$G$181) -> 180 | C6: =AVERAGE(Dataset!$G$2:$G$181) -> 1.3321311 | D6: =STDEV(Dataset!$G$2:$G$181) -> 0.55325949 | E6: =MIN(Dataset!$G$2:$G$181) -> 0.1 | F6: =MAX(Dataset!$G$2:$G$181) -> 2.987 | H6: 1.332 | I6: 0.553 | J6: 0.1 | K6: 2.987 | L6: =IF(AND(ROUND(C6,3)=H6,ROUND(D6,3)=I6,ROUND(E6,3)=J6,ROUND(F6,3)=K6),"✓","✗") -> ✓
A7: Interest Coverage | B7: =COUNT(Dataset!$H$2:$H$181) -> 180 | C7: =AVERAGE(Dataset!$H$2:$H$181) -> 4.4287367 | D7: =STDEV(Dataset!$H$2:$H$181) -> 3.3314003 | E7: =MIN(Dataset!$H$2:$H$181) -> -1.5 | F7: =MAX(Dataset!$H$2:$H$181) -> 15.768 | H7: 4.429 | I7: 3.331 | J7: -1.5 | K7: 15.768 | L7: =IF(AND(ROUND(C7,3)=H7,ROUND(D7,3)=I7,ROUND(E7,3)=J7,ROUND(F7,3)=K7),"✓","✗") -> ✓
A8: ROA | B8: =COUNT(Dataset!$I$2:$I$181) -> 180 | C8: =AVERAGE(Dataset!$I$2:$I$181) -> 0.042189444 | D8: =STDEV(Dataset!$I$2:$I$181) -> 0.063778094 | E8: =MIN(Dataset!$I$2:$I$181) -> -0.139 | F8: =MAX(Dataset!$I$2:$I$181) -> 0.2 | H8: 0.042 | I8: 0.064 | J8: -0.139 | K8: 0.2 | L8: =IF(AND(ROUND(C8,3)=H8,ROUND(D8,3)=I8,ROUND(E8,3)=J8,ROUND(F8,3)=K8),"✓","✗") -> ✓
A9: Net Profit Margin | B9: =COUNT(Dataset!$J$2:$J$181) -> 180 | C9: =AVERAGE(Dataset!$J$2:$J$181) -> 0.04499 | D9: =STDEV(Dataset!$J$2:$J$181) -> 0.068104121 | E9: =MIN(Dataset!$J$2:$J$181) -> -0.194 | F9: =MAX(Dataset!$J$2:$J$181) -> 0.223 | H9: 0.045 | I9: 0.068 | J9: -0.194 | K9: 0.223 | L9: =IF(AND(ROUND(C9,3)=H9,ROUND(D9,3)=I9,ROUND(E9,3)=J9,ROUND(F9,3)=K9),"✓","✗") -> ✓
A10: Asset Turnover | B10: =COUNT(Dataset!$K$2:$K$181) -> 180 | C10: =AVERAGE(Dataset!$K$2:$K$181) -> 1.19862 | D10: =STDEV(Dataset!$K$2:$K$181) -> 0.41260005 | E10: =MIN(Dataset!$K$2:$K$181) -> 0.2 | F10: =MAX(Dataset!$K$2:$K$181) -> 2.241 | H10: 1.199 | I10: 0.413 | J10: 0.2 | K10: 2.241 | L10: =IF(AND(ROUND(C10,3)=H10,ROUND(D10,3)=I10,ROUND(E10,3)=J10,ROUND(F10,3)=K10),"✓","✗") -> ✓
A11: Firm Size (ln TA) | B11: =COUNT(Dataset!$L$2:$L$181) -> 180 | C11: =AVERAGE(Dataset!$L$2:$L$181) -> 14.681274 | D11: =STDEV(Dataset!$L$2:$L$181) -> 1.2506005 | E11: =MIN(Dataset!$L$2:$L$181) -> 11.139 | F11: =MAX(Dataset!$L$2:$L$181) -> 17.378 | H11: 14.681 | I11: 1.251 | J11: 11.139 | K11: 17.378 | L11: =IF(AND(ROUND(C11,3)=H11,ROUND(D11,3)=I11,ROUND(E11,3)=J11,ROUND(F11,3)=K11),"✓","✗") -> ✓

Sheet T5.2 t-Test
A1: Table 5.2 – Independent Samples t-Test (Welch) by Firm Status
A3: Indicator | B3: N (Non-Bankrupt) | C3: N (Bankrupt) | D3: Mean (Non-Bankrupt) | E3: SD (Non-Bankrupt) | F3: Mean (Bankrupt) | G3: SD (Bankrupt) | H3: Mean Difference | I3: t-value (Welch) | J3: df (Welch) | K3: p-value (2-tailed) | L3: Sig. (α = 0.05) | N3: Reported t | O3: Reported p | P3: Match t
A4: Current Ratio | B4: =COUNTIF(Dataset!$B$2:$B$181,0) -> 134 | C4: =COUNTIF(Dataset!$B$2:$B$181,1) -> 46 | D4: =AVERAGEIF(Dataset!$B$2:$B$181,0,Dataset!$E$2:$E$181) -> 1.5770433 | E4: =SQRT(SUMPRODUCT((Dataset!$B$2:$B$181=0)*(Dataset!$E$2:$E$181-D4)^2)/(B4-1)) -> 0.49842592 | F4: =AVERAGEIF(Dataset!$B$2:$B$181,1,Dataset!$E$2:$E$181) -> 1.3914 | G4: =SQRT(SUMPRODUCT((Dataset!$B$2:$B$181=1)*(Dataset!$E$2:$E$181-F4)^2)/(C4-1)) -> 0.55544407 | H4: =D4-F4 -> 0.18564328 | I4: =H4/SQRT(E4^2/B4+G4^2/C4) -> 2.0064141 | J4: =(E4^2/B4+G4^2/C4)^2/((E4^2/B4)^2/(B4-1)+(G4^2/C4)^2/(C4-1)) -> 71.468793 | K4: =TDIST(ABS(I4),J4,2) -> 0.048621976 | L4: =IF(K4<0.05,"Yes","No") -> Yes | N4: 2.006 | O4: 0.049 | P4: =IF(ROUND(I4,3)=N4,"✓","✗") -> ✓
A5: Quick Ratio | B5: =COUNTIF(Dataset!$B$2:$B$181,0) -> 134 | C5: =COUNTIF(Dataset!$B$2:$B$181,1) -> 46 | D5: =AVERAGEIF(Dataset!$B$2:$B$181,0,Dataset!$F$2:$F$181) -> 1.2145985 | E5: =SQRT(SUMPRODUCT((Dataset!$B$2:$B$181=0)*(Dataset!$F$2:$F$181-D5)^2)/(B5-1)) -> 0.51405803 | F5: =AVERAGEIF(Dataset!$B$2:$B$181,1,Dataset!$F$2:$F$181) -> 0.89540217 | G5: =SQRT(SUMPRODUCT((Dataset!$B$2:$B$181=1)*(Dataset!$F$2:$F$181-F5)^2)/(C5-1)) -> 0.46319375 | H5: =D5-F5 -> 0.31919633 | I5: =H5/SQRT(E5^2/B5+G5^2/C5) -> 3.9183179 | J5: =(E5^2/B5+G5^2/C5)^2/((E5^2/B5)^2/(B5-1)+(G5^2/C5)^2/(C5-1)) -> 85.902303 | K5: =TDIST(ABS(I5),J5,2) -> 0.00017970828 | L5: =IF(K5<0.05,"Yes","No") -> Yes | N5: 3.918 | O5: 0.000 | P5: =IF(ROUND(I5,3)=N5,"✓","✗") -> ✓
A6: Debt-to-Equity | B6: =COUNTIF(Dataset!$B$2:$B$181,0) -> 134 | C6: =COUNTIF(Dataset!$B$2:$B$181,1) -> 46 | D6: =AVERAGEIF(Dataset!$B$2:$B$181,0,Dataset!$G$2:$G$181) -> 1.2176022 | E6: =SQRT(SUMPRODUCT((Dataset!$B$2:$B$181=0)*(Dataset!$G$2:$G$181-D6)^2)/(B6-1)) -> 0.49237797 | F6: =AVERAGEIF(Dataset!$B$2:$B$181,1,Dataset!$G$2:$G$181) -> 1.6657587 | G6: =SQRT(SUMPRODUCT((Dataset!$B$2:$B$181=1)*(Dataset!$G$2:$G$181-F6)^2)/(C6-1)) -> 0.59009226 | H6: =D6-F6 -> -0.44815646 | I6: =H6/SQRT(E6^2/B6+G6^2/C6) -> -4.6275572 | J6: =(E6^2/B6+G6^2/C6)^2/((E6^2/B6)^2/(B6-1)+(G6^2/C6)^2/(C6-1)) -> 67.771345 | K6: =TDIST(ABS(I6),J6,2) -> 1.7470522e-05 | L6: =IF(K6<0.05,"Yes","No") -> Yes | N6: -4.628 | O6: <0.001 | P6: =IF(ROUND(I6,3)=N6,"✓","✗") -> ✓
A7: Interest Coverage | B7: =COUNTIF(Dataset!$B$2:$B$181,0) -> 134 | C7: =COUNTIF(Dataset!$B$2:$B$181,1) -> 46 | D7: =AVERAGEIF(Dataset!$B$2:$B$181,0,Dataset!$H$2:$H$181) -> 4.9605955 | E7: =SQRT(SUMPRODUCT((Dataset!$B$2:$B$181=0)*(Dataset!$H$2:$H$181-D7)^2)/(B7-1)) -> 3.4067451 | F7: =AVERAGEIF(Dataset!$B$2:$B$181,1,Dataset!$H$2:$H$181) -> 2.8794087 | G7: =SQRT(SUMPRODUCT((Dataset!$B$2:$B$181=1)*(Dataset!$H$2:$H$181-F7)^2)/(C7-1)) -> 2.5589589 | H7: =D7-F7 -> 2.0811868 | I7: =H7/SQRT(E7^2/B7+G7^2/C7) -> 4.3493717 | J7: =(E7^2/B7+G7^2/C7)^2/((E7^2/B7)^2/(B7-1)+(G7^2/C7)^2/(C7-1)) -> 103.45815 | K7: =TDIST(ABS(I7),J7,2) -> 3.2186941e-05 | L7: =IF(K7<0.05,"Yes","No") -> Yes | N7: 4.349 | O7: <0.001 | P7: =IF(ROUND(I7,3)=N7,"✓","✗") -> ✓
A8: ROA | B8: =COUNTIF(Dataset!$B$2:$B$181,0) -> 134 | C8: =COUNTIF(Dataset!$B$2:$B$181,1) -> 46 | D8: =AVERAGEIF(Dataset!$B$2:$B$181,0,Dataset!$I$2:$I$181) -> 0.056395522 | E8: =SQRT(SUMPRODUCT((Dataset!$B$2:$B$181=0)*(Dataset!$I$2:$I$181-D8)^2)/(B8-1)) -> 0.060242551 | F8: =AVERAGEIF(Dataset!$B$2:$B$181,1,Dataset!$I$2:$I$181) -> 0.00080652174 | G8: =SQRT(SUMPRODUCT((Dataset!$B$2:$B$181=1)*(Dataset!$I$2:$I$181-F8)^2)/(C8-1)) -> 0.055699501 | H8: =D8-F8 -> 0.055589001 | I8: =H8/SQRT(E8^2/B8+G8^2/C8) -> 5.7175461 | J8: =(E8^2/B8+G8^2/C8)^2/((E8^2/B8)^2/(B8-1)+(G8^2/C8)^2/(C8-1)) -> 83.824004 | K8: =TDIST(ABS(I8),J8,2) -> 1.6531141e-07 | L8: =IF(K8<0.05,"Yes","No") -> Yes | N8: 5.718 | O8: <0.001 | P8: =IF(ROUND(I8,3)=N8,"✓","✗") -> ✓
A9: Net Profit Margin | B9: =COUNTIF(Dataset!$B$2:$B$181,0) -> 134 | C9: =COUNTIF(Dataset!$B$2:$B$181,1) -> 46 | D9: =AVERAGEIF(Dataset!$B$2:$B$181,0,Dataset!$J$2:$J$181) -> 0.065300746 | E9: =SQRT(SUMPRODUCT((Dataset!$B$2:$B$181=0)*(Dataset!$J$2:$J$181-D9)^2)/(B9-1)) -> 0.055415508 | F9: =AVERAGEIF(Dataset!$B$2:$B$181,1,Dataset!$J$2:$J$181) -> -0.014176087 | G9: =SQRT(SUMPRODUCT((Dataset!$B$2:$B$181=1)*(Dataset!$J$2:$J$181-F9)^2)/(C9-1)) -> 0.067576867 | H9: =D9-F9 -> 0.079476833 | I9: =H9/SQRT(E9^2/B9+G9^2/C9) -> 7.1898498 | J9: =(E9^2/B9+G9^2/C9)^2/((E9^2/B9)^2/(B9-1)+(G9^2/C9)^2/(C9-1)) -> 66.966601 | K9: =TDIST(ABS(I9),J9,2) -> 7.4375788e-10 | L9: =IF(K9<0.05,"Yes","No") -> Yes | N9: 7.19 | O9: <0.001 | P9: =IF(ROUND(I9,3)=N9,"✓","✗") -> ✓
A10: Asset Turnover | B10: =COUNTIF(Dataset!$B$2:$B$181,0) -> 134 | C10: =COUNTIF(Dataset!$B$2:$B$181,1) -> 46 | D10: =AVERAGEIF(Dataset!$B$2:$B$181,0,Dataset!$K$2:$K$181) -> 1.2714022 | E10: =SQRT(SUMPRODUCT((Dataset!$B$2:$B$181=0)*(Dataset!$K$2:$K$181-D10)^2)/(B10-1)) -> 0.40548618 | F10: =AVERAGEIF(Dataset!$B$2:$B$181,1,Dataset!$K$2:$K$181) -> 0.98660217 | G10: =SQRT(SUMPRODUCT((Dataset!$B$2:$B$181=1)*(Dataset!$K$2:$K$181-F10)^2)/(C10-1)) -> 0.35985831 | H10: =D10-F10 -> 0.28480006 | I10: =H10/SQRT(E10^2/B10+G10^2/C10) -> 4.4795271 | J10: =(E10^2/B10+G10^2/C10)^2/((E10^2/B10)^2/(B10-1)+(G10^2/C10)^2/(C10-1)) -> 87.172534 | K10: =TDIST(ABS(I10),J10,2) -> 2.2628385e-05 | L10: =IF(K10<0.05,"Yes","No") -> Yes | N10: 4.48 | O10: <0.001 | P10: =IF(ROUND(I10,3)=N10,"✓","✗") -> ✓
A11: Firm Size (ln TA) | B11: =COUNTIF(Dataset!$B$2:$B$181,0) -> 134 | C11: =COUNTIF(Dataset!$B$2:$B$181,1) -> 46 | D11: =AVERAGEIF(Dataset!$B$2:$B$181,0,Dataset!$L$2:$L$181) -> 14.781401 | E11: =SQRT(SUMPRODUCT((Dataset!$B$2:$B$181=0)*(Dataset!$L$2:$L$181-D11)^2)/(B11-1)) -> 1.2384271 | F11: =AVERAGEIF(Dataset!$B$2:$B$181,1,Dataset!$L$2:$L$181) -> 14.389602 | G11: =SQRT(SUMPRODUCT((Dataset!$B$2:$B$181=1)*(Dataset!$L$2:$L$181-F11)^2)/(C11-1)) -> 1.2535926 | H11: =D11-F11 -> 0.39179857 | I11: =H11/SQRT(E11^2/B11+G11^2/C11) -> 1.8345948 | J11: =(E11^2/B11+G11^2/C11)^2/((E11^2/B11)^2/(B11-1)+(G11^2/C11)^2/(C11-1)) -> 77.269023 | K11: =TDIST(ABS(I11),J11,2) -> 0.07042834 | L11: =IF(K11<0.05,"Yes","No") -> No | N11: 1.835 | O11: 0.070 | P11: =IF(ROUND(I11,3)=N11,"✓","✗") -> ✓

Sheet Fig5.3 Correlation
A1: Figure 5.3 – Pearson Correlation Matrix of Financial Indicators (N = 180)
B3: Current Ratio | C3: Quick Ratio | D3: Debt-to-Equity | E3: Interest Coverage | F3: ROA | G3: Net Profit Margin | H3: Asset Turnover | I3: Firm Size (ln TA)
A4: Current Ratio | B4: =CORREL(Dataset!$E$2:$E$181,Dataset!$E$2:$E$181) -> 1 | C4: =CORREL(Dataset!$E$2:$E$181,Dataset!$F$2:$F$181) -> 0.094003151 | D4: =CORREL(Dataset!$E$2:$E$181,Dataset!$G$2:$G$181) -> -0.13333632 | E4: =CORREL(Dataset!$E$2:$E$181,Dataset!$H$2:$H$181) -> 0.120777 | F4: =CORREL(Dataset!$E$2:$E$181,Dataset!$I$2:$I$181) -> 0.10406948 | G4: =CORREL(Dataset!$E$2:$E$181,Dataset!$J$2:$J$181) -> 0.095986409 | H4: =CORREL(Dataset!$E$2:$E$181,Dataset!$K$2:$K$181) -> 0.062882808 | I4: =CORREL(Dataset!$E$2:$E$181,Dataset!$L$2:$L$181) -> 0.043986155
A5: Quick Ratio | B5: =CORREL(Dataset!$F$2:$F$181,Dataset!$E$2:$E$181) -> 0.094003151 | C5: =CORREL(Dataset!$F$2:$F$181,Dataset!$F$2:$F$181) -> 1 | D5: =CORREL(Dataset!$F$2:$F$181,Dataset!$G$2:$G$181) -> -0.073909763 | E5: =CORREL(Dataset!$F$2:$F$181,Dataset!$H$2:$H$181) -> 0.049249837 | F5: =CORREL(Dataset!$F$2:$F$181,Dataset!$I$2:$I$181) -> 0.19006005 | G5: =CORREL(Dataset!$F$2:$F$181,Dataset!$J$2:$J$181) -> 0.098604 | H5: =CORREL(Dataset!$F$2:$F$181,Dataset!$K$2:$K$181) -> 0.096254271 | I5: =CORREL(Dataset!$F$2:$F$181,Dataset!$L$2:$L$181) -> 0.0069903102
A6: Debt-to-Equity | B6: =CORREL(Dataset!$G$2:$G$181,Dataset!$E$2:$E$181) -> -0.13333632 | C6: =CORREL(Dataset!$G$2:$G$181,Dataset!$F$2:$F$181) -> -0.073909763 | D6: =CORREL(Dataset!$G$2:$G$181,Dataset!$G$2:$G$181) -> 1 | E6: =CORREL(Dataset!$G$2:$G$181,Dataset!$H$2:$H$181) -> -0.19651297 | F6: =CORREL(Dataset!$G$2:$G$181,Dataset!$I$2:$I$181) -> -0.2260706 | G6: =CORREL(Dataset!$G$2:$G$181,Dataset!$J$2:$J$181) -> -0.22967632 | H6: =CORREL(Dataset!$G$2:$G$181,Dataset!$K$2:$K$181) -> -0.10762993 | I6: =CORREL(Dataset!$G$2:$G$181,Dataset!$L$2:$L$181) -> -0.12329762
A7: Interest Coverage | B7: =CORREL(Dataset!$H$2:$H$181,Dataset!$E$2:$E$181) -> 0.120777 | C7: =CORREL(Dataset!$H$2:$H$181,Dataset!$F$2:$F$181) -> 0.049249837 | D7: =CORREL(Dataset!$H$2:$H$181,Dataset!$G$2:$G$181) -> -0.19651297 | E7: =CORREL(Dataset!$H$2:$H$181,Dataset!$H$2:$H$181) -> 1 | F7: =CORREL(Dataset!$H$2:$H$181,Dataset!$I$2:$I$181) -> 0.17727628 | G7: =CORREL(Dataset!$H$2:$H$181,Dataset!$J$2:$J$181) -> 0.13056444 | H7: =CORREL(Dataset!$H$2:$H$181,Dataset!$K$2:$K$181) -> 0.028040186 | I7: =CORREL(Dataset!$H$2:$H$181,Dataset!$L$2:$L$181) -> 0.17399898
A8: ROA | B8: =CORREL(Dataset!$I$2:$I$181,Dataset!$E$2:$E$181) -> 0.10406948 | C8: =CORREL(Dataset!$I$2:$I$181,Dataset!$F$2:$F$181) -> 0.19006005 | D8: =CORREL(Dataset!$I$2:$I$181,Dataset!$G$2:$G$181) -> -0.2260706 | E8: =CORREL(Dataset!$I$2:$I$181,Dataset!$H$2:$H$181) -> 0.17727628 | F8: =CORREL(Dataset!$I$2:$I$181,Dataset!$I$2:$I$181) -> 1 | G8: =CORREL(Dataset!$I$2:$I$181,Dataset!$J$2:$J$181) -> 0.14696252 | H8: =CORREL(Dataset!$I$2:$I$181,Dataset!$K$2:$K$181) -> 0.11006786 | I8: =CORREL(Dataset!$I$2:$I$181,Dataset!$L$2:$L$181) -> 0.077255234
A9: Net Profit Margin | B9: =CORREL(Dataset!$J$2:$J$181,Dataset!$E$2:$E$181) -> 0.095986409 | C9: =CORREL(Dataset!$J$2:$J$181,Dataset!$F$2:$F$181) -> 0.098604 | D9: =CORREL(Dataset!$J$2:$J$181,Dataset!$G$2:$G$181) -> -0.22967632 | E9: =CORREL(Dataset!$J$2:$J$181,Dataset!$H$2:$H$181) -> 0.13056444 | F9: =CORREL(Dataset!$J$2:$J$181,Dataset!$I$2:$I$181) -> 0.14696252 | G9: =CORREL(Dataset!$J$2:$J$181,Dataset!$J$2:$J$181) -> 1 | H9: =CORREL(Dataset!$J$2:$J$181,Dataset!$K$2:$K$181) -> 0.089792664 | I9: =CORREL(Dataset!$J$2:$J$181,Dataset!$L$2:$L$181) -> 0.15782687
A10: Asset Turnover | B10: =CORREL(Dataset!$K$2:$K$181,Dataset!$E$2:$E$181) -> 0.062882808 | C10: =CORREL(Dataset!$K$2:$K$181,Dataset!$F$2:$F$181) -> 0.096254271 | D10: =CORREL(Dataset!$K$2:$K$181,Dataset!$G$2:$G$181) -> -0.10762993 | E10: =CORREL(Dataset!$K$2:$K$181,Dataset!$H$2:$H$181) -> 0.028040186 | F10: =CORREL(Dataset!$K$2:$K$181,Dataset!$I$2:$I$181) -> 0.11006786 | G10: =CORREL(Dataset!$K$2:$K$181,Dataset!$J$2:$J$181) -> 0.089792664 | H10: =CORREL(Dataset!$K$2:$K$181,Dataset!$K$2:$K$181) -> 1 | I10: =CORREL(Dataset!$K$2:$K$181,Dataset!$L$2:$L$181) -> 0.042687247
A11: Firm Size (ln TA) | B11: =CORREL(Dataset!$L$2:$L$181,Dataset!$E$2:$E$181) -> 0.043986155 | C11: =CORREL(Dataset!$L$2:$L$181,Dataset!$F$2:$F$181) -> 0.0069903102 | D11: =CORREL(Dataset!$L$2:$L$181,Dataset!$G$2:$G$181) -> -0.12329762 | E11: =CORREL(Dataset!$L$2:$L$181,Dataset!$H$2:$H$181) -> 0.17399898 | F11: =CORREL(Dataset!$L$2:$L$181,Dataset!$I$2:$I$181) -> 0.077255234 | G11: =CORREL(Dataset!$L$2:$L$181,Dataset!$J$2:$J$181) -> 0.15782687 | H11: =CORREL(Dataset!$L$2:$L$181,Dataset!$K$2:$K$181) -> 0.042687247 | I11: =CORREL(Dataset!$L$2:$L$181,Dataset!$L$2:$L$181) -> 1
A13: Reported (Figure 5.3):
B14: Current Ratio | C14: Quick Ratio | D14: Debt-to-Equity | E14: Interest Coverage | F14: ROA | G14: Net Profit Margin | H14: Asset Turnover | I14: Firm Size (ln TA)
A15: Current Ratio | B15: 1 | C15: 0.09 | D15: -0.13 | E15: 0.12 | F15: 0.1 | G15: 0.1 | H15: 0.06 | I15: 0.04
A16: Quick Ratio | B16: 0.09 | C16: 1 | D16: -0.07 | E16: 0.05 | F16: 0.19 | G16: 0.1 | H16: 0.1 | I16: 0.01
A17: Debt-to-Equity | B17: -0.13 | C17: -0.07 | D17: 1 | E17: -0.2 | F17: -0.23 | G17: -0.23 | H17: -0.11 | I17: -0.12
A18: Interest Coverage | B18: 0.12 | C18: 0.05 | D18: -0.2 | E18: 1 | F18: 0.18 | G18: 0.13 | H18: 0.03 | I18: 0.17
A19: ROA | B19: 0.1 | C19: 0.19 | D19: -0.23 | E19: 0.18 | F19: 1 | G19: 0.15 | H19: 0.11 | I19: 0.08
A20: Net Profit Margin | B20: 0.1 | C20: 0.1 | D20: -0.23 | E20: 0.13 | F20: 0.15 | G20: 1 | H20: 0.09 | I20: 0.16
A21: Asset Turnover | B21: 0.06 | C21: 0.1 | D21: -0.11 | E21: 0.03 | F21: 0.11 | G21: 0.09 | H21: 1 | I21: 0.04
A22: Firm Size (ln TA) | B22: 0.04 | C22: 0.01 | D22: -0.12 | E22: 0.17 | F22: 0.08 | G22: 0.16 | H22: 0.04 | I22: 1
A24: All cells match: | B24: =IF(SUMPRODUCT(--(ROUND(B4:I11,2)<>B15:I22))=0,"✓","✗") -> ✓

Sheet ML Test Set
A1: Test set (n = 54) – predicted probability of bankruptcy per model (threshold = 0.50)
A3: Firm_ID | B3: Actual Status | C3: P(Bankrupt) – Logistic Regression | D3: Predicted – LR | E3: P(Bankrupt) – Random Forest | F3: Predicted – RF | G3: P(Bankrupt) – SVM (RBF) | H3: Predicted – SVM
A4: F008 | B4: =INDEX(Dataset!$B$2:$B$181,MATCH(A4,Dataset!$A$2:$A$181,0)) -> 0 | C4: 0.0137 | D4: =IF(C4>=0.5,1,0) -> 0 | E4: 0.005 | F4: =IF(E4>=0.5,1,0) -> 0 | G4: 0.0224 | H4: =IF(G4>=0.5,1,0) -> 0
A5: F009 | B5: =INDEX(Dataset!$B$2:$B$181,MATCH(A5,Dataset!$A$2:$A$181,0)) -> 0 | C5: 0.0347 | D5: =IF(C5>=0.5,1,0) -> 0 | E5: 0.095 | F5: =IF(E5>=0.5,1,0) -> 0 | G5: 0.0445 | H5: =IF(G5>=0.5,1,0) -> 0
A6: F013 | B6: =INDEX(Dataset!$B$2:$B$181,MATCH(A6,Dataset!$A$2:$A$181,0)) -> 1 | C6: 0.9743 | D6: =IF(C6>=0.5,1,0) -> 1 | E6: 0.6 | F6: =IF(E6>=0.5,1,0) -> 1 | G6: 0.9275 | H6: =IF(G6>=0.5,1,0) -> 1
A7: F017 | B7: =INDEX(Dataset!$B$2:$B$181,MATCH(A7,Dataset!$A$2:$A$181,0)) -> 0 | C7: 0.6312 | D7: =IF(C7>=0.5,1,0) -> 1 | E7: 0.47 | F7: =IF(E7>=0.5,1,0) -> 0 | G7: 0.495 | H7: =IF(G7>=0.5,1,0) -> 0
A8: F020 | B8: =INDEX(Dataset!$B$2:$B$181,MATCH(A8,Dataset!$A$2:$A$181,0)) -> 0 | C8: 0.0534 | D8: =IF(C8>=0.5,1,0) -> 0 | E8: 0.13 | F8: =IF(E8>=0.5,1,0) -> 0 | G8: 0.0744 | H8: =IF(G8>=0.5,1,0) -> 0
A9: F022 | B9: =INDEX(Dataset!$B$2:$B$181,MATCH(A9,Dataset!$A$2:$A$181,0)) -> 0 | C9: 0.1855 | D9: =IF(C9>=0.5,1,0) -> 0 | E9: 0.235 | F9: =IF(E9>=0.5,1,0) -> 0 | G9: 0.1931 | H9: =IF(G9>=0.5,1,0) -> 0
A10: F025 | B10: =INDEX(Dataset!$B$2:$B$181,MATCH(A10,Dataset!$A$2:$A$181,0)) -> 1 | C10: 0.9739 | D10: =IF(C10>=0.5,1,0) -> 1 | E10: 0.765 | F10: =IF(E10>=0.5,1,0) -> 1 | G10: 0.9533 | H10: =IF(G10>=0.5,1,0) -> 1
A11: F026 | B11: =INDEX(Dataset!$B$2:$B$181,MATCH(A11,Dataset!$A$2:$A$181,0)) -> 1 | C11: 0.9253 | D11: =IF(C11>=0.5,1,0) -> 1 | E11: 0.655 | F11: =IF(E11>=0.5,1,0) -> 1 | G11: 0.8747 | H11: =IF(G11>=0.5,1,0) -> 1
A12: F031 | B12: =INDEX(Dataset!$B$2:$B$181,MATCH(A12,Dataset!$A$2:$A$181,0)) -> 0 | C12: 0.3184 | D12: =IF(C12>=0.5,1,0) -> 0 | E12: 0.495 | F12: =IF(E12>=0.5,1,0) -> 0 | G12: 0.4729 | H12: =IF(G12>=0.5,1,0) -> 0
A13: F038 | B13: =INDEX(Dataset!$B$2:$B$181,MATCH(A13,Dataset!$A$2:$A$181,0)) -> 0 | C13: 0.01 | D13: =IF(C13>=0.5,1,0) -> 0 | E13: 0.055 | F13: =IF(E13>=0.5,1,0) -> 0 | G13: 0.0261 | H13: =IF(G13>=0.5,1,0) -> 0
A14: F040 | B14: =INDEX(Dataset!$B$2:$B$181,MATCH(A14,Dataset!$A$2:$A$181,0)) -> 0 | C14: 0.0277 | D14: =IF(C14>=0.5,1,0) -> 0 | E14: 0.225 | F14: =IF(E14>=0.5,1,0) -> 0 | G14: 0.1458 | H14: =IF(G14>=0.5,1,0) -> 0
A15: F041 | B15: =INDEX(Dataset!$B$2:$B$181,MATCH(A15,Dataset!$A$2:$A$181,0)) -> 0 | C15: 0.2171 | D15: =IF(C15>=0.5,1,0) -> 0 | E15: 0.35 | F15: =IF(E15>=0.5,1,0) -> 0 | G15: 0.1982 | H15: =IF(G15>=0.5,1,0) -> 0
... A57: F177 | B57: =INDEX(Dataset!$B$2:$B$181,MATCH(A57,Dataset!$A$2:$A$181,0)) -> 0 | C57: 0.0303 | D57: =IF(C57>=0.5,1,0) -> 0 | E57: 0.1349 | F57: =IF(E57>=0.5,1,0) -> 0 | G57: 0.0904 | H57: =IF(G57>=0.5,1,0) -> 0

Sheet T5.3 Model Metrics
A1: Table 5.3 – Performance Comparison of Classification Models (Test Set, n = 54)
A3: Model | B3: TN | C3: FP | D3: FN | E3: TP | F3: Accuracy | G3: Precision | H3: Recall | I3: F1-Score | J3: AUC | L3: Rep. Accuracy | M3: Rep. Precision | N3: Rep. Recall | O3: Rep. F1 | P3: Rep. AUC | Q3: Match
A4: Logistic Regression | B4: =COUNTIFS('ML Test Set'!$B$4:$B$57,0,'ML Test Set'!$D$4:$D$57,0) -> 35 | C4: =COUNTIFS('ML Test Set'!$B$4:$B$57,0,'ML Test Set'!$D$4:$D$57,1) -> 5 | D4: =COUNTIFS('ML Test Set'!$B$4:$B$57,1,'ML Test Set'!$D$4:$D$57,0) -> 4 | E4: =COUNTIFS('ML Test Set'!$B$4:$B$57,1,'ML Test Set'!$D$4:$D$57,1) -> 10 | F4: =(B4+E4)/SUM(B4:E4) -> 0.83333333 | G4: =E4/(E4+C4) -> 0.66666667 | H4: =E4/(E4+D4) -> 0.71428571 | I4: =2*G4*H4/(G4+H4) -> 0.68965517 | J4: =SUMPRODUCT(('ML Test Set'!$B$4:$B$57=1)*COUNTIFS('ML Test Set'!$B$4:$B$57,0,'ML Test Set'!$C$4:$C$57,"<"&'ML Test Set'!$C$4:$C$57))/(COUNTIF('ML Test Set'!$B$4:$B$57,1)*COUNTIF('ML Test Set'!$B$4:$B$57,0)) -> 0.91428571 | L4: 0.833 | M4: 0.667 | N4: 0.714 | O4: 0.69 | P4: 0.914 | Q4: =IF(AND(ROUND(F4,3)=L4,ROUND(G4,3)=M4,ROUND(H4,3)=N4,ROUND(I4,3)=O4,ROUND(J4,3)=P4),"✓","✗") -> ✓
A5: Random Forest | B5: =COUNTIFS('ML Test Set'!$B$4:$B$57,0,'ML Test Set'!$F$4:$F$57,0) -> 39 | C5: =COUNTIFS('ML Test Set'!$B$4:$B$57,0,'ML Test Set'!$F$4:$F$57,1) -> 1 | D5: =COUNTIFS('ML Test Set'!$B$4:$B$57,1,'ML Test Set'!$F$4:$F$57,0) -> 6 | E5: =COUNTIFS('ML Test Set'!$B$4:$B$57,1,'ML Test Set'!$F$4:$F$57,1) -> 8 | F5: =(B5+E5)/SUM(B5:E5) -> 0.87037037 | G5: =E5/(E5+C5) -> 0.88888889 | H5: =E5/(E5+D5) -> 0.57142857 | I5: =2*G5*H5/(G5+H5) -> 0.69565217 | J5: =SUMPRODUCT(('ML Test Set'!$B$4:$B$57=1)*COUNTIFS('ML Test Set'!$B$4:$B$57,0,'ML Test Set'!$E$4:$E$57,"<"&'ML Test Set'!$E$4:$E$57))/(COUNTIF('ML Test Set'!$B$4:$B$57,1)*COUNTIF('ML Test Set'!$B$4:$B$57,0)) -> 0.86785714 | L5: 0.87 | M5: 0.889 | N5: 0.571 | O5: 0.696 | P5: 0.868 | Q5: =IF(AND(ROUND(F5,3)=L5,ROUND(G5,3)=M5,ROUND(H5,3)=N5,ROUND(I5,3)=O5,ROUND(J5,3)=P5),"✓","✗") -> ✓
A6: SVM (RBF) | B6: =COUNTIFS('ML Test Set'!$B$4:$B$57,0,'ML Test Set'!$H$4:$H$57,0) -> 37 | C6: =COUNTIFS('ML Test Set'!$B$4:$B$57,0,'ML Test Set'!$H$4:$H$57,1) -> 3 | D6: =COUNTIFS('ML Test Set'!$B$4:$B$57,1,'ML Test Set'!$H$4:$H$57,0) -> 5 | E6: =COUNTIFS('ML Test Set'!$B$4:$B$57,1,'ML Test Set'!$H$4:$H$57,1) -> 9 | F6: =(B6+E6)/SUM(B6:E6) -> 0.85185185 | G6: =E6/(E6+C6) -> 0.75 | H6: =E6/(E6+D6) -> 0.64285714 | I6: =2*G6*H6/(G6+H6) -> 0.69230769 | J6: =SUMPRODUCT(('ML Test Set'!$B$4:$B$57=1)*COUNTIFS('ML Test Set'!$B$4:$B$57,0,'ML Test Set'!$G$4:$G$57,"<"&'ML Test Set'!$G$4:$G$57))/(COUNTIF('ML Test Set'!$B$4:$B$57,1)*COUNTIF('ML Test Set'!$B$4:$B$57,0)) -> 0.88214286 | L6: 0.852 | M6: 0.75 | N6: 0.643 | O6: 0.692 | P6: 0.882 | Q6: =IF(AND(ROUND(F6,3)=L6,ROUND(G6,3)=M6,ROUND(H6,3)=N6,ROUND(I6,3)=O6,ROUND(J6,3)=P6),"✓","✗") -> ✓
